drainage-0.1.7.dist-info/METADATA
drainage-0.1.7.dist-info/WHEEL
drainage-0.1.7.dist-info/licenses/LICENSE
drainage/__init__.py
drainage/drainage.cpython-39-darwin.so
drainage-0.1.7.dist-info/RECORD
