Metadata-Version: 2.3
Name: drainage
Version: 0.1.7
Classifier: Development Status :: 3 - Alpha
Classifier: Intended Audience :: Developers
Classifier: License :: OSI Approved :: MIT License
Classifier: Programming Language :: Python :: 3
Classifier: Programming Language :: Python :: 3.8
Classifier: Programming Language :: Python :: 3.9
Classifier: Programming Language :: Python :: 3.10
Classifier: Programming Language :: Python :: 3.11
Classifier: Programming Language :: Python :: 3.12
Classifier: Programming Language :: Rust
Classifier: Topic :: Software Development :: Libraries :: Python Modules
Classifier: Topic :: Database
License-File: LICENSE
Summary: High-performance data lake health analyzer for Delta Lake and Apache Iceberg
Keywords: data-lake,delta-lake,iceberg,s3,analytics,data-engineering
Author-email: Daniel Beach <daniel@example.com>
License: MIT
Requires-Python: >=3.8
Project-URL: Homepage, https://github.com/danielbeach/drainage
Project-URL: Repository, https://github.com/danielbeach/drainage
Project-URL: Documentation, https://github.com/danielbeach/drainage#readme
Project-URL: Issues, https://github.com/danielbeach/drainage/issues
